pytba_captcha.py
pytba_captcha-0.0.1.dist-info/LICENSE
pytba_captcha-0.0.1.dist-info/METADATA
pytba_captcha-0.0.1.dist-info/WHEEL
pytba_captcha-0.0.1.dist-info/top_level.txt
pytba_captcha-0.0.1.dist-info/RECORD
